fhe_http/__init__.py
fhe_http/fhe.cpython-310-darwin.so
fhe_http/assembler/__init__.py
fhe_http/assembler/assembler.py
fhe_http/assembler/configs.py
fhe_http/assembler/parser.out
fhe_http/assembler/parsetab.py
fhe_http-0.2.47.dist-info/METADATA
fhe_http-0.2.47.dist-info/WHEEL
fhe_http-0.2.47.dist-info/top_level.txt
fhe_http-0.2.47.dist-info/RECORD
