Metadata-Version: 2.1
Name: fhe-http
Version: 0.2.47
Summary: This is an test package for Python Fhe Http 
Home-page: https://github.com/spockwall/fhe-http
Author: spockwall
Author-email: e1e1e1n9n9n9@gmail.com
Classifier: Programming Language :: Rust
Classifier: Programming Language :: Python :: Implementation :: CPython
Classifier: Programming Language :: Python :: Implementation :: PyPy
Requires-Python: >=3.8
Requires-Dist: ply >=3.11
Requires-Dist: setuptools-rust >=1.9.0
Requires-Dist: setuptools >=68.2.2
Requires-Dist: wheel >=0.43.0
